lhub_cli/__init__.py
lhub_cli/actions.py
lhub_cli/args_with_subargs.py
lhub_cli/config.py
lhub_cli/connection_manager.py
lhub_cli/encryption.py
lhub_cli/log.py
lhub_cli/main.py
lhub_cli/shell.py
lhub_cli/statics.py
lhub_cli/common/__init__.py
lhub_cli/common/args.py
lhub_cli/common/config.py
lhub_cli/common/output.py
lhub_cli/common/shell.py
lhub_cli/exceptions/__init__.py
lhub_cli/exceptions/app.py
lhub_cli/exceptions/base.py
lhub_cli/exceptions/encryption.py
lhub_cli/features/__init__.py
lhub_cli/features/commands.py
lhub_cli-0.1.2.0.dist-info/METADATA
lhub_cli-0.1.2.0.dist-info/WHEEL
lhub_cli-0.1.2.0.dist-info/top_level.txt
lhub_cli-0.1.2.0.dist-info/RECORD
