Metadata-Version: 2.1
Name: lhub-cli
Version: 0.1.2.0
Summary: LogicHub CLI
Home-page: https://github.com/deathbywedgie/lhub_cli
Author: Chad Roberts
Author-email: chad@logichub.com
License: UNKNOWN
Project-URL: Bug Tracker, https://github.com/deathbywedgie/lhub_cli/issues
Keywords: python,lhub,LogicHub,api,security,cli
Platform: UNKNOWN
Classifier: Development Status :: 1 - Planning
Classifier: Intended Audience :: End Users/Desktop
Classifier: Intended Audience :: System Administrators
Classifier: Intended Audience :: Information Technology
Classifier: Programming Language :: Python :: 3.10
Classifier: Natural Language :: English
Requires-Dist: lhub (~=0.2.6)
Requires-Dist: configobj (>=5.0.6)
Requires-Dist: dataclasses-json (>=0.5.6)
Requires-Dist: rsa (>=4.8)
Requires-Dist: requests
Requires-Dist: tabulate
Requires-Dist: colorama
Requires-Dist: structlog
Requires-Dist: progressbar2
